{
  "sections": [
    {
      "name": "Bắt đầu",
      "slug": "getting started",
      "articles": [
        {
          "id": "165365457",
          "topics": [
            "Bắt đầu",
            "Thanh toán"
          ],
          "title": "Tối ưu hóa Mua hàng Trực tuyến với Bitcoin: Hướng dẫn Sử dụng Bitcoin cho Giao dịch",
          "slug": "streamlining-online-purchases-with-bitcoin-a-guide-to-using-bitcoin-for-transacti",
          "authorName": "Maxi Millie",
          "authorPicture": {
            "url": "https://www.datocms-assets.com/101962/1694419898-maximillie1.png"
          },
          "_publishedAt": "2023-10-05T06:03:51+01:00",
          "description": "Khám phá sự tiện lợi của việc mua hàng trực tuyến bằng Bitcoin. Tìm hiểu cách sử dụng Bitcoin một cách dễ dàng cho các giao dịch an toàn và liền mạch trong hướng dẫn toàn diện của chúng tôi.",
          "thumbnail": {
            "url": "https://www.datocms-assets.com/101962/1686858962-bb10-img1.png"
          },
          "contentBlock": [],
          "seo": {
            "description": "Learn how to effortlessly use Bitcoin for secure and seamless transactions in our comprehensive guide",
            "title": "Streamlining Online Purchases with Bitcoin",
            "twitterCard": null,
            "image": {
              "width": 1024,
              "height": 1024,
              "title": null,
              "alt": null,
              "url": "https://www.datocms-assets.com/101962/1686858962-bb10-img1.png"
            }
          }
        },
        {
          "id": "165362142",
          "topics": [
            "Bắt đầu",
            "Chứng minh công việc",
            "Đào"
          ],
          "title": "Khám phá sức mạnh của Đào Bitcoin: Giới thiệu về Thuật toán Chứng minh công việc",
          "slug": "unlocking-the-power-of-bitcoin-mining-an-introduction-to-proof-of-work-algorithms",
          "authorName": "Maxi Millie",
          "authorPicture": {
            "url": "https://www.datocms-assets.com/101962/1694419898-maximillie1.png"
          },
          "_publishedAt": "2023-10-05T05:55:09+01:00",
          "description": "Khám phá thế giới đào Bitcoin và khái niệm hấp dẫn về thuật toán chứng minh công việc. Khám phá tiềm năng và phần thưởng của công nghệ biến đổi này.",
          "thumbnail": {
            "url": "https://www.datocms-assets.com/101962/1686858321-bb9-img0edited.png"
          },
          "contentBlock": [],
          "seo": {
            "description": "Delve into the world of Bitcoin mining and the fascinating concept of proof-of-work algorithms. ",
            "title": " An Introduction to Proof-of-Work Algorithms",
            "twitterCard": null,
            "image": {
              "width": 1024,
              "height": 1024,
              "title": null,
              "alt": null,
              "url": "https://www.datocms-assets.com/101962/1686858321-bb9-img0edited.png"
            }
          }
        },
        {
          "id": "165340146",
          "topics": [
            "Bắt đầu",
            "Chứng minh công việc"
          ],
          "title": "An ninh kinh tế của Bitcoin: Làm thế nào Chứng minh công việc tạo ra một mạng lưới an toàn và bảo mật",
          "slug": "the-economic-security-of-bitcoin-how-proof-of-work-enables-a-safe-and-secure-netw",
          "authorName": "Maxi Millie",
          "authorPicture": {
            "url": "https://www.datocms-assets.com/101962/1694419898-maximillie1.png"
          },
          "_publishedAt": "2023-10-05T05:53:43+01:00",
          "description": "Khám phá an ninh kinh tế của Bitcoin và sức mạnh của chứng minh công việc. Khám phá cách công nghệ sáng tạo này đảm bảo một mạng lưới an toàn và bảo mật cho tương lai.",
          "thumbnail": {
            "url": "https://www.datocms-assets.com/101962/1686856982-bb8-img1.png"
          },
          "contentBlock": [],
          "seo": {
            "description": "Explore how this innovative technology ensures a safe and secure network for the future.",
            "title": "The Economic Security of Bitcoin: Proof-of-Work",
            "twitterCard": null,
            "image": {
              "width": 1024,
              "height": 1024,
              "title": null,
              "alt": null,
              "url": "https://www.datocms-assets.com/101962/1686856982-bb8-img1.png"
            }
          }
        },
        {
          "id": "165340050",
          "topics": [
            "Getting Started",
            "Legal"
          ],
          "title": "Navigating the Legal and Regulatory Landscape of Bitcoin: Understanding the Rules and Opportunities",
          "slug": "navigating-the-legal-and-regulatory-landscape-of-bitcoin-understanding-the-rules",
          "authorName": "Maxi Millie",
          "authorPicture": {
            "url": "https://www.datocms-assets.com/101962/1694419898-maximillie1.png"
          },
          "_publishedAt": "2023-10-05T05:52:05+01:00",
          "description": "Stay informed and compliant with our comprehensive guide to the legal and regulatory landscape of Bitcoin. Navigate the complexities of cryptocurrency with confidence.",
          "thumbnail": {
            "url": "https://www.datocms-assets.com/101962/1686855768-bb7-img1edited.png"
          },
          "contentBlock": [],
          "seo": {
            "description": "Stay informed and compliant with our comprehensive guide to the legal and regulatory landscape of Bitcoin. ",
            "title": "Navigating the Legal and Regulatory Landscape of Bitcoin",
            "twitterCard": null,
            "image": {
              "width": 1024,
              "height": 1024,
              "title": null,
              "alt": null,
              "url": "https://www.datocms-assets.com/101962/1686855768-bb7-img1edited.png"
            }
          }
        },
        {
          "id": "165337859",
          "topics": [
            "Getting Started",
            "Security"
          ],
          "title": "The Future of Bitcoin Storage: An Introduction to Bitcoin Wallets and Innovative Storage Solutions",
          "slug": "the-future-of-bitcoin-storage-an-introduction-to-bitcoin-wallets-and-innovative-s",
          "authorName": "Maxi Millie",
          "authorPicture": {
            "url": "https://www.datocms-assets.com/101962/1694419898-maximillie1.png"
          },
          "_publishedAt": "2023-10-05T05:50:52+01:00",
          "description": "Explore the world of Bitcoin wallets and innovative storage solutions. Learn how to secure and manage your digital assets with our comprehensive introductory guide.",
          "thumbnail": {
            "url": "https://www.datocms-assets.com/101962/1686854653-bb6-img1.png"
          },
          "contentBlock": [],
          "seo": {
            "description": "Learn how to secure and manage your digital assets with our comprehensive introductory guide.",
            "title": "An Introduction to Bitcoin Wallets and Storage Solutions",
            "twitterCard": null,
            "image": {
              "width": 1024,
              "height": 1024,
              "title": null,
              "alt": null,
              "url": "https://www.datocms-assets.com/101962/1686854653-bb6-img1.png"
            }
          }
        },
        {
          "id": "165005184",
          "topics": [
            "Getting Started"
          ],
          "title": "The Art of Researching and Evaluating Bitcoin Exchanges: A Guide for Investors",
          "slug": "the-art-of-researching-and-evaluating-bitcoin-exchanges-a-guide-for-investors",
          "authorName": "Maxi Millie",
          "authorPicture": {
            "url": "https://www.datocms-assets.com/101962/1694419898-maximillie1.png"
          },
          "_publishedAt": "2023-10-05T05:50:29+01:00",
          "description": "Unlock the secrets of researching and evaluating Bitcoin exchanges. Discover essential tips and insights for confident investing.",
          "thumbnail": {
            "url": "https://www.datocms-assets.com/101962/1686794861-bb5-img1.png"
          },
          "contentBlock": [],
          "seo": {
            "description": "Unlock the secrets of researching and evaluating Bitcoin exchanges. Discover essential tips and insights for confident investing.",
            "title": "The Art of Researching and Evaluating Bitcoin Exchanges",
            "twitterCard": null,
            "image": {
              "width": 1024,
              "height": 1024,
              "title": null,
              "alt": null,
              "url": "https://www.datocms-assets.com/101962/1686794861-bb5-img1.png"
            }
          }
        },
        {
          "id": "164973196",
          "topics": [
            "Getting Started",
            "History"
          ],
          "title": "The History and Evolution of Bitcoin",
          "slug": "the-history-and-evolution-of-bitcoin",
          "authorName": "Maxi Millie",
          "authorPicture": {
            "url": "https://www.datocms-assets.com/101962/1694419898-maximillie1.png"
          },
          "_publishedAt": "2023-10-05T05:38:06+01:00",
          "description": "Trace the captivating journey of Bitcoin's history and evolution. Uncover the origins, milestones, and transformative impact of this groundbreaking technology.",
          "thumbnail": {
            "url": "https://www.datocms-assets.com/101962/1686789411-bb2-img1edited.png"
          },
          "contentBlock": [],
          "seo": {
            "description": "Trace the captivating journey of Bitcoin's history and evolution. Uncover the origins, milestones, and transformative impact of this groundbreaking technology.",
            "title": "The History and Evolution of Bitcoin",
            "twitterCard": null,
            "image": {
              "width": 1024,
              "height": 1024,
              "title": null,
              "alt": null,
              "url": "https://www.datocms-assets.com/101962/1686789411-bb2-img1edited.png"
            }
          }
        },
        {
          "id": "165004875",
          "topics": [
            "Getting Started",
            "Security"
          ],
          "title": "How to Keep Your Bitcoins Safe in the Digital Age",
          "slug": "how-to-keep-your-bitcoins-safe-in-the-digital-age",
          "authorName": "Maxi Millie",
          "authorPicture": {
            "url": "https://www.datocms-assets.com/101962/1694419898-maximillie1.png"
          },
          "_publishedAt": "2023-10-05T05:28:36+01:00",
          "description": "Safeguard your Bitcoins in the digital era with our expert tips and strategies. Learn essential techniques to protect your valuable digital assets.",
          "thumbnail": {
            "url": "https://www.datocms-assets.com/101962/1686791711-bb3-img1.png"
          },
          "contentBlock": [],
          "seo": {
            "description": "Safeguard your Bitcoins in the digital era with our expert tips and strategies. Learn essential techniques to protect your valuable digital assets.",
            "title": "How to Keep Your Bitcoins Safe in the Digital Age",
            "twitterCard": null,
            "image": {
              "width": 1024,
              "height": 1024,
              "title": null,
              "alt": null,
              "url": "https://www.datocms-assets.com/101962/1686791711-bb3-img1.png"
            }
          }
        },
        {
          "id": "165005107",
          "topics": [
            "Getting Started",
            "Exchange"
          ],
          "title": "The Simplified Guide to Buying and Selling Bitcoins",
          "slug": "the-simplified-guide-to-buying-and-selling-bitcoins",
          "authorName": "Maxi Millie",
          "authorPicture": {
            "url": "https://www.datocms-assets.com/101962/1694419898-maximillie1.png"
          },
          "_publishedAt": "2023-10-05T05:26:26+01:00",
          "description": "Master the art of buying and selling Bitcoin with our simplified guide. Learn step-by-step strategies and expert tips.",
          "thumbnail": {
            "url": "https://www.datocms-assets.com/101962/1686793200-bb4-img1.png"
          },
          "contentBlock": [],
          "seo": {
            "description": "Master the art of buying and selling Bitcoin with our simplified guide. Learn step-by-step strategies and expert tips.",
            "title": "The Simplified Guide to Buying and Selling Bitcoins",
            "twitterCard": null,
            "image": {
              "width": 1024,
              "height": 1024,
              "title": null,
              "alt": null,
              "url": "https://www.datocms-assets.com/101962/1686793200-bb4-img1.png"
            }
          }
        },
        {
          "id": "164904960",
          "topics": [
            "Getting Started"
          ],
          "title": "Think Differently About Bitcoin: The Future of Decentralized Currency",
          "slug": "think-differently-about-bitcoin-the-future-of-decentralized-currency",
          "authorName": "Maxi Millie",
          "authorPicture": {
            "url": "https://www.datocms-assets.com/101962/1694419898-maximillie1.png"
          },
          "_publishedAt": "2023-10-05T04:44:43+01:00",
          "description": "Discover how to think differently about Bitcoin and its revolutionary potential with our captivating blog post. Explore Don't miss out!",
          "thumbnail": {
            "url": "https://www.datocms-assets.com/101962/1686760978-bb1-img1.png"
          },
          "contentBlock": [],
          "seo": {
            "description": "Discover how to think differently about Bitcoin and its revolutionary potential with our captivating blog post. Explore Don't miss out!",
            "title": "Think Differently About Bitcoin",
            "twitterCard": "summary_large_image",
            "image": {
              "width": 1024,
              "height": 1024,
              "title": null,
              "alt": null,
              "url": "https://www.datocms-assets.com/101962/1686760978-bb1-img1.png"
            }
          }
        }
      ]
    },
    {
      "name": "Thanh toán",
      "slug": " payments",
      "articles": [
        {
          "id": "165365457",
          "topics": [
            "Bắt đầu",
            "Thanh toán"
          ],
          "title": "Tối ưu hóa Mua hàng Trực tuyến với Bitcoin: Hướng dẫn Sử dụng Bitcoin cho Giao dịch",
          "slug": "streamlining-online-purchases-with-bitcoin-a-guide-to-using-bitcoin-for-transacti",
          "authorName": "Maxi Millie",
          "authorPicture": {
            "url": "https://www.datocms-assets.com/101962/1694419898-maximillie1.png"
          },
          "_publishedAt": "2023-10-05T06:03:51+01:00",
          "description": "Khám phá sự tiện lợi của việc mua hàng trực tuyến bằng Bitcoin. Tìm hiểu cách sử dụng Bitcoin một cách dễ dàng cho các giao dịch an toàn và liền mạch trong hướng dẫn toàn diện của chúng tôi.",
          "thumbnail": {
            "url": "https://www.datocms-assets.com/101962/1686858962-bb10-img1.png"
          },
          "contentBlock": [],
          "seo": {
            "description": "Learn how to effortlessly use Bitcoin for secure and seamless transactions in our comprehensive guide",
            "title": "Streamlining Online Purchases with Bitcoin",
            "twitterCard": null,
            "image": {
              "width": 1024,
              "height": 1024,
              "title": null,
              "alt": null,
              "url": "https://www.datocms-assets.com/101962/1686858962-bb10-img1.png"
            }
          }
        }
      ]
    },
    {
      "name": "Chứng minh công việc",
      "slug": "proof-of-work",
      "articles": [
        {
          "id": "165362142",
          "topics": [
            "Bắt đầu",
            "Chứng minh công việc",
            "Đào"
          ],
          "title": "Khám phá sức mạnh của Đào Bitcoin: Giới thiệu về Thuật toán Chứng minh công việc",
          "slug": "unlocking-the-power-of-bitcoin-mining-an-introduction-to-proof-of-work-algorithms",
          "authorName": "Maxi Millie",
          "authorPicture": {
            "url": "https://www.datocms-assets.com/101962/1694419898-maximillie1.png"
          },
          "_publishedAt": "2023-10-05T05:55:09+01:00",
          "description": "Khám phá thế giới đào Bitcoin và khái niệm hấp dẫn về thuật toán chứng minh công việc. Khám phá tiềm năng và phần thưởng của công nghệ biến đổi này.",
          "thumbnail": {
            "url": "https://www.datocms-assets.com/101962/1686858321-bb9-img0edited.png"
          },
          "contentBlock": [],
          "seo": {
            "description": "Delve into the world of Bitcoin mining and the fascinating concept of proof-of-work algorithms. ",
            "title": " An Introduction to Proof-of-Work Algorithms",
            "twitterCard": null,
            "image": {
              "width": 1024,
              "height": 1024,
              "title": null,
              "alt": null,
              "url": "https://www.datocms-assets.com/101962/1686858321-bb9-img0edited.png"
            }
          }
        },
        {
          "id": "165340146",
          "topics": [
            "Bắt đầu",
            "Chứng minh công việc"
          ],
          "title": "An ninh kinh tế của Bitcoin: Làm thế nào Chứng minh công việc tạo điều kiện cho một mạng lưới an toàn và bảo mật",
          "slug": "the-economic-security-of-bitcoin-how-proof-of-work-enables-a-safe-and-secure-netw",
          "authorName": "Maxi Millie",
          "authorPicture": {
            "url": "https://www.datocms-assets.com/101962/1694419898-maximillie1.png"
          },
          "_publishedAt": "2023-10-05T05:53:43+01:00",
          "description": "Khám phá an ninh kinh tế của Bitcoin và sức mạnh của chứng minh công việc. Khám phá cách công nghệ sáng tạo này đảm bảo một mạng lưới an toàn và bảo mật cho tương lai.",
          "thumbnail": {
            "url": "https://www.datocms-assets.com/101962/1686856982-bb8-img1.png"
          },
          "contentBlock": [],
          "seo": {
            "description": "Explore how this innovative technology ensures a safe and secure network for the future.",
            "title": "The Economic Security of Bitcoin: Proof-of-Work",
            "twitterCard": null,
            "image": {
              "width": 1024,
              "height": 1024,
              "title": null,
              "alt": null,
              "url": "https://www.datocms-assets.com/101962/1686856982-bb8-img1.png"
            }
          }
        }
      ]
    },
    {
      "name": "Đào",
      "slug": "mining",
      "articles": [
        {
          "id": "165362142",
          "topics": [
            "Bắt đầu",
            "Chứng minh công việc",
            "Đào"
          ],
          "title": "Khám phá sức mạnh của Đào Bitcoin: Giới thiệu về Thuật toán Chứng minh công việc",
          "slug": "unlocking-the-power-of-bitcoin-mining-an-introduction-to-proof-of-work-algorithms",
          "authorName": "Maxi Millie",
          "authorPicture": {
            "url": "https://www.datocms-assets.com/101962/1694419898-maximillie1.png"
          },
          "_publishedAt": "2023-10-05T05:55:09+01:00",
          "description": "Khám phá thế giới đào Bitcoin và khái niệm hấp dẫn về thuật toán chứng minh công việc. Khám phá tiềm năng và phần thưởng của công nghệ biến đổi này.",
          "thumbnail": {
            "url": "https://www.datocms-assets.com/101962/1686858321-bb9-img0edited.png"
          },
          "contentBlock": [],
          "seo": {
            "description": "Delve into the world of Bitcoin mining and the fascinating concept of proof-of-work algorithms. ",
            "title": " An Introduction to Proof-of-Work Algorithms",
            "twitterCard": null,
            "image": {
              "width": 1024,
              "height": 1024,
              "title": null,
              "alt": null,
              "url": "https://www.datocms-assets.com/101962/1686858321-bb9-img0edited.png"
            }
          }
        }
      ]
    },
    {
      "name": "Pháp lý",
      "slug": "legal",
      "articles": [
        {
          "id": "165340050",
          "topics": [
            "Bắt đầu",
            "Pháp lý"
          ],
          "title": "Định hướng Phong cảnh Pháp lý và Quy định của Bitcoin: Hiểu các Quy tắc và Cơ hội",
          "slug": "navigating-the-legal-and-regulatory-landscape-of-bitcoin-understanding-the-rules",
          "authorName": "Maxi Millie",
          "authorPicture": {
            "url": "https://www.datocms-assets.com/101962/1694419898-maximillie1.png"
          },
          "_publishedAt": "2023-10-05T05:52:05+01:00",
          "description": "Hãy thông báo và tuân thủ với hướng dẫn toàn diện của chúng tôi về phong cảnh pháp lý và quy định của Bitcoin. Điều hướng sự phức tạp của tiền điện tử với sự tự tin.",
          "thumbnail": {
            "url": "https://www.datocms-assets.com/101962/1686855768-bb7-img1edited.png"
          },
          "contentBlock": [],
          "seo": {
            "description": "Stay informed and compliant with our comprehensive guide to the legal and regulatory landscape of Bitcoin. ",
            "title": "Navigating the Legal and Regulatory Landscape of Bitcoin",
            "twitterCard": null,
            "image": {
              "width": 1024,
              "height": 1024,
              "title": null,
              "alt": null,
              "url": "https://www.datocms-assets.com/101962/1686855768-bb7-img1edited.png"
            }
          }
        }
      ]
    },
    {
      "name": "Bảo mật",
      "slug": "security",
      "articles": [
        {
          "id": "165337859",
          "topics": [
            "Bắt đầu",
            "Bảo mật"
          ],
          "title": "Tương lai của việc lưu trữ Bitcoin: Giới thiệu về ví Bitcoin và các giải pháp lưu trữ sáng tạo",
          "slug": "the-future-of-bitcoin-storage-an-introduction-to-bitcoin-wallets-and-innovative-s",
          "authorName": "Maxi Millie",
          "authorPicture": {
            "url": "https://www.datocms-assets.com/101962/1694419898-maximillie1.png"
          },
          "_publishedAt": "2023-10-05T05:50:52+01:00",
          "description": "Khám phá thế giới của ví Bitcoin và các giải pháp lưu trữ sáng tạo. Tìm hiểu cách bảo mật và quản lý tài sản số của bạn với hướng dẫn giới thiệu toàn diện của chúng tôi.",
          "thumbnail": {
            "url": "https://www.datocms-assets.com/101962/1686854653-bb6-img1.png"
          },
          "contentBlock": [],
          "seo": {
            "description": "Learn how to secure and manage your digital assets with our comprehensive introductory guide.",
            "title": "An Introduction to Bitcoin Wallets and Storage Solutions",
            "twitterCard": null,
            "image": {
              "width": 1024,
              "height": 1024,
              "title": null,
              "alt": null,
              "url": "https://www.datocms-assets.com/101962/1686854653-bb6-img1.png"
            }
          }
        },
        {
          "id": "165004875",
          "topics": [
            "Bắt đầu",
            "Bảo mật"
          ],
          "title": "Làm thế nào để giữ an toàn Bitcoin của bạn trong kỷ nguyên số",
          "slug": "how-to-keep-your-bitcoins-safe-in-the-digital-age",
          "authorName": "Maxi Millie",
          "authorPicture": {
            "url": "https://www.datocms-assets.com/101962/1694419898-maximillie1.png"
          },
          "_publishedAt": "2023-10-05T05:28:36+01:00",
          "description": "Bảo vệ Bitcoin của bạn trong kỷ nguyên số với các mẹo và chiến lược của chuyên gia. Học các kỹ thuật thiết yếu để bảo vệ tài sản số quý giá của bạn.",
          "thumbnail": {
            "url": "https://www.datocms-assets.com/101962/1686791711-bb3-img1.png"
          },
          "contentBlock": [],
          "seo": {
            "description": "Safeguard your Bitcoins in the digital era with our expert tips and strategies. Learn essential techniques to protect your valuable digital assets.",
            "title": "How to Keep Your Bitcoins Safe in the Digital Age",
            "twitterCard": null,
            "image": {
              "width": 1024,
              "height": 1024,
              "title": null,
              "alt": null,
              "url": "https://www.datocms-assets.com/101962/1686791711-bb3-img1.png"
            }
          }
        }
      ]
    },
    {
      "name": "Lịch sử",
      "slug": "history",
      "articles": [
        {
          "id": "164973196",
          "topics": [
            "Bắt đầu",
            "Lịch sử"
          ],
          "title": "Lịch sử và Sự phát triển của Bitcoin",
          "slug": "the-history-and-evolution-of-bitcoin",
          "authorName": "Maxi Millie",
          "authorPicture": {
            "url": "https://www.datocms-assets.com/101962/1694419898-maximillie1.png"
          },
          "_publishedAt": "2023-10-05T05:38:06+01:00",
          "description": "Theo dõi hành trình hấp dẫn của lịch sử và sự phát triển của Bitcoin. Khám phá nguồn gốc, các cột mốc quan trọng và tác động biến đổi của công nghệ mang tính bước ngoặt này.",
          "thumbnail": {
            "url": "https://www.datocms-assets.com/101962/1686789411-bb2-img1edited.png"
          },
          "contentBlock": [],
          "seo": {
            "description": "Trace the captivating journey of Bitcoin's history and evolution. Uncover the origins, milestones, and transformative impact of this groundbreaking technology.",
            "title": "The History and Evolution of Bitcoin",
            "twitterCard": null,
            "image": {
              "width": 1024,
              "height": 1024,
              "title": null,
              "alt": null,
              "url": "https://www.datocms-assets.com/101962/1686789411-bb2-img1edited.png"
            }
          }
        }
      ]
    },
    {
      "name": "Trao đổi",
      "slug": "exchange",
      "articles": [
        {
          "id": "165005107",
          "topics": [
            "Bắt đầu",
            "Trao đổi"
          ],
          "title": "Hướng dẫn Đơn giản để Mua và Bán Bitcoin",
          "slug": "the-simplified-guide-to-buying-and-selling-bitcoins",
          "authorName": "Maxi Millie",
          "authorPicture": {
            "url": "https://www.datocms-assets.com/101962/1694419898-maximillie1.png"
          },
          "_publishedAt": "2023-10-05T05:26:26+01:00",
          "description": "Thành thạo nghệ thuật mua và bán Bitcoin với hướng dẫn đơn giản của chúng tôi. Học các chiến lược từng bước và mẹo từ chuyên gia.",
          "thumbnail": {
            "url": "https://www.datocms-assets.com/101962/1686793200-bb4-img1.png"
          },
          "contentBlock": [],
          "seo": {
            "description": "Master the art of buying and selling Bitcoin with our simplified guide. Learn step-by-step strategies and expert tips.",
            "title": "The Simplified Guide to Buying and Selling Bitcoins",
            "twitterCard": null,
            "image": {
              "width": 1024,
              "height": 1024,
              "title": null,
              "alt": null,
              "url": "https://www.datocms-assets.com/101962/1686793200-bb4-img1.png"
            }
          }
        }
      ]
    }
  ],
  "pageSeo": {
    "pageSeo": {
      "description": "Lorem ipsum dolor sit amet",
      "image": null,
      "title": "Bitcoin | Bitcash Blog",
      "twitterCard": "summary_large_image"
    },
    "description": "Tiên phong trong kỷ nguyên vàng số",
    "title": "Bitcoin",
    "seoType": "bitcoin",
    "id": "178642411",
    "_createdAt": "2023-07-24T18:41:46+01:00"
  }
}